{
  "project_info": {
    "project_number": "869641026445",
    "project_id": "study-companion-5f354",
    "storage_bucket": "study-companion-5f354.firebasestorage.app"
  },
  "client": [
    {
      "client_info": {
        "mobilesdk_app_id": "1:869641026445:android:3b82772f726ca9914edbc4",
        "android_client_info": {
          "package_name": "com.example.studycompanion_app"
        }
      },
      "oauth_client": [],
      "api_key": [
        {
          "current_key": "AIzaSyDaoUy205HARXHACb9Tp3k02QSrKqFNC6M"
        }
      ],
      "services": {
        "appinvite_service": {
          "other_platform_oauth_client": []
        }
      }
    }
  ],
  "configuration_version": "1"
}